zettelkasten/#add.py#
zettelkasten/__init__.py
zettelkasten/__main__.py
zettelkasten/add.py
zettelkasten/cli.py
zettelkasten/defaults.py
zettelkasten/initialize.py
zettelkasten/monkeypatch.py
zettelkasten/py.typed
zettelkasten/setup.py
zettelkasten-0.2.3.dist-info/entry_points.txt
zettelkasten-0.2.3.dist-info/LICENSE
zettelkasten-0.2.3.dist-info/WHEEL
zettelkasten-0.2.3.dist-info/METADATA
zettelkasten-0.2.3.dist-info/RECORD
