Metadata-Version: 2.1
Name: zettelkasten
Version: 0.2.3
Summary: CLI interface for managing a folder based zettelkasten using emacs org-mode file zettels and a bibtex reference system
Home-page: https://github.com/tZ3ma/zettelkasten
License: MIT
Keywords: zettelkasten,org-mode,bibtex
Author: tZ3ma
Author-email: mathias.ammon@tuhh.de
Requires-Python: >=3.7,<4.0
Classifier: Development Status :: 3 - Alpha
Classifier: Intended Audience :: Science/Research
Classifier: License :: OSI Approved :: MIT License
Classifier: Operating System :: OS Independent
Classifier: Programming Language :: Python :: 3
Classifier: Programming Language :: Python :: 3.7
Classifier: Programming Language :: Python :: 3.8
Classifier: Programming Language :: Python :: 3.9
Classifier: Topic :: Scientific/Engineering :: Human Machine Interfaces
Requires-Dist: importlib_metadata (>=3.4.0,<4.0.0); python_version < "3.8"
Requires-Dist: rich (>=9.13.0,<10.0.0)
Requires-Dist: typer[all] (>=0.3.2,<0.4.0)
Project-URL: Repository, https://github.com/tZ3ma/zettelkasten
